cognite/client/__init__.py
cognite/client/_api_client.py
cognite/client/_cognite_client.py
cognite/client/_http_client.py
cognite/client/_version.py
cognite/client/beta.py
cognite/client/exceptions.py
cognite/client/experimental.py
cognite/client/testing.py
cognite/client/_api/__init__.py
cognite/client/_api/assets.py
cognite/client/_api/data_sets.py
cognite/client/_api/datapoints.py
cognite/client/_api/entity_matching.py
cognite/client/_api/events.py
cognite/client/_api/extractionpipelines.py
cognite/client/_api/files.py
cognite/client/_api/iam.py
cognite/client/_api/labels.py
cognite/client/_api/login.py
cognite/client/_api/raw.py
cognite/client/_api/relationships.py
cognite/client/_api/sequences.py
cognite/client/_api/synthetic_time_series.py
cognite/client/_api/templates.py
cognite/client/_api/three_d.py
cognite/client/_api/time_series.py
cognite/client/_api/model_hosting/__init__.py
cognite/client/_api/model_hosting/models.py
cognite/client/_api/model_hosting/schedules.py
cognite/client/_api/model_hosting/source_packages.py
cognite/client/_api/model_hosting/versions.py
cognite/client/data_classes/__init__.py
cognite/client/data_classes/_base.py
cognite/client/data_classes/assets.py
cognite/client/data_classes/contextualization.py
cognite/client/data_classes/data_sets.py
cognite/client/data_classes/datapoints.py
cognite/client/data_classes/events.py
cognite/client/data_classes/extractionpipelines.py
cognite/client/data_classes/files.py
cognite/client/data_classes/iam.py
cognite/client/data_classes/labels.py
cognite/client/data_classes/login.py
cognite/client/data_classes/raw.py
cognite/client/data_classes/relationships.py
cognite/client/data_classes/sequences.py
cognite/client/data_classes/shared.py
cognite/client/data_classes/templates.py
cognite/client/data_classes/three_d.py
cognite/client/data_classes/time_series.py
cognite/client/data_classes/model_hosting/__init__.py
cognite/client/data_classes/model_hosting/models.py
anders_sdk_jupyterlite-2.34.0.dist-info/LICENSE
anders_sdk_jupyterlite-2.34.0.dist-info/METADATA
anders_sdk_jupyterlite-2.34.0.dist-info/WHEEL
anders_sdk_jupyterlite-2.34.0.dist-info/top_level.txt
anders_sdk_jupyterlite-2.34.0.dist-info/RECORD
