Metadata-Version: 2.1
Name: anders-sdk-jupyterlite
Version: 2.34.0
Summary: Jupyterlite client library for Cognite Data Fusion (CDF)
Home-page: https://cognite-sdk-python.readthedocs-hosted.com
Author: Erlend Vollset
Author-email: erlend.vollset@cognite.com
License: UNKNOWN
Download-URL: https://github.com/cognitedata/cognite-sdk-python/archive/2.34.0.tar.gz
Platform: UNKNOWN
Requires-Python: >=3.5
Requires-Dist: requests (<3.0.0,>=2.21.0)
Requires-Dist: pandas
Requires-Dist: requests-oauthlib (==1.3.0)
